v3d_py_helper.libs/libstdc++-a9383cce.so.6.0.28
v3d_py_helper.libs/libgcc_s-a04fdf82.so.1
v3d_py_helper-0.4.1.dist-info/RECORD
v3d_py_helper-0.4.1.dist-info/WHEEL
v3d_py_helper-0.4.1.dist-info/LICENSE
v3d_py_helper-0.4.1.dist-info/top_level.txt
v3d_py_helper-0.4.1.dist-info/METADATA
v3dpy/__init__.py
v3dpy/image_processing/__init__.py
v3dpy/neuron_utilities/profiling.cpython-312-x86_64-linux-musl.so
v3dpy/neuron_utilities/swc_handler.py
v3dpy/neuron_utilities/profiling.pyx
v3dpy/neuron_utilities/__init__.py
v3dpy/loaders/raw.pyx
v3dpy/loaders/__init__.py
v3dpy/loaders/pbd.cpython-312-x86_64-linux-musl.so
v3dpy/loaders/raw.cpython-312-x86_64-linux-musl.so
v3dpy/loaders/pbd.pyx
v3dpy/terafly/tiff_manage.pyx
v3dpy/terafly/volume_managers.pyx
v3dpy/terafly/format_managers.pxd
v3dpy/terafly/volume_managers.cpython-312-x86_64-linux-musl.so
v3dpy/terafly/tiff_manage.cpython-312-x86_64-linux-musl.so
v3dpy/terafly/format_managers.cpython-312-x86_64-linux-musl.so
v3dpy/terafly/__init__.py
v3dpy/terafly/tiff_manage.pxd
v3dpy/terafly/config.py
v3dpy/terafly/format_managers.pyx
