Metadata-Version: 2.1
Name: v3d-py-helper
Version: 0.4.1
Summary: Make Vaa3D functions available for high-performance python computation.
Author-email: Zuohan Zhao <zzhmark@126.com>, Yufeng Liu <yufeng_liu@seu.edu.cn>
License: MIT License
Project-URL: GitHub Project, https://github.com/SEU-ALLEN-codebase/v3d-py-helper
Project-URL: Documentation, https://SEU-ALLEN-codebase.github.io/v3d-py-helper
Project-URL: Vaa3D Source, https://github.com/Vaa3D/v3d_external
Keywords: vaa3d,neuron-morphology,image-processing
Classifier: Programming Language :: Python :: 3
Classifier: License :: OSI Approved :: MIT License
Classifier: Operating System :: OS Independent
Requires-Python: >=3.10
License-File: LICENSE
Requires-Dist: numpy
Provides-Extra: docs
Requires-Dist: pdoc ; extra == 'docs'
